Subhan_STT/__init__.py
subhan_stt-0.1.dist-info/METADATA
subhan_stt-0.1.dist-info/WHEEL
subhan_stt-0.1.dist-info/top_level.txt
subhan_stt-0.1.dist-info/RECORD
